cocoro/__init__.py
cocoro/__main__.py
cocoro/__version__.py
cocoro/cli.py
cocoro/core.py
cocoro/py.typed
cocoro-0.1.5.dist-info/LICENSE
cocoro-0.1.5.dist-info/METADATA
cocoro-0.1.5.dist-info/WHEEL
cocoro-0.1.5.dist-info/entry_points.txt
cocoro-0.1.5.dist-info/RECORD
