Metadata-Version: 2.1
Name: cocoro
Version: 0.1.5
Summary: Utilities to use Sharp, COCORO API
Home-page: https://github.com/rcmdnk/cocoro
License: Apache-2.0
Keywords: Sharp,API
Author: rcmdnk
Author-email: rcmdnk@gmail.com
Requires-Python: >=3.8,<4.0
Classifier: License :: OSI Approved :: Apache Software License
Classifier: Programming Language :: Python :: 3
Classifier: Programming Language :: Python :: 3.8
Classifier: Programming Language :: Python :: 3.9
Classifier: Programming Language :: Python :: 3.10
Classifier: Programming Language :: Python :: 3.11
Classifier: Programming Language :: Python :: 3.12
Requires-Dist: PyYAML (>=6.0.0,<7.0.0)
Requires-Dist: fire (>=0.5.0,<0.6.0)
Requires-Dist: requests (>=2.25.1,<3.0.0)
Project-URL: Repository, https://github.com/rcmdnk/cocoro
